case_mapping/__init__.py
case_mapping/base.py
case_mapping/case/__init__.py
case_mapping/case/investigation.py
case_mapping/directory.py
case_mapping/drafting/__init__.py
case_mapping/drafting/entities.py
case_mapping/mix_utils.py
case_mapping/uco/__init__.py
case_mapping/uco/action.py
case_mapping/uco/core.py
case_mapping/uco/identity.py
case_mapping/uco/location.py
case_mapping/uco/observable.py
case_mapping/uco/role.py
case_mapping/uco/tool.py
case_mapping/uco/types.py
case_mapping-0.2.1.dist-info/LICENSE.txt
case_mapping-0.2.1.dist-info/METADATA
case_mapping-0.2.1.dist-info/WHEEL
case_mapping-0.2.1.dist-info/RECORD
