Metadata-Version: 2.3
Name: case-mapping
Version: 0.2.1
Summary: Classes to support representation of the CASE Cyber Ontology
License: Apache-2.0
Maintainer: Cyber Domain Ontology Maintainers
Maintainer-email: operations@cyberdomainontology.org
Requires-Python: >=3.9,<4.0
Classifier: Development Status :: 3 - Alpha
Classifier: Environment :: Console
Classifier: License :: OSI Approved :: Apache Software License
Classifier: Operating System :: OS Independent
Classifier: Programming Language :: Python :: 3
Classifier: Programming Language :: Python :: 3.9
Classifier: Programming Language :: Python :: 3.10
Classifier: Programming Language :: Python :: 3.11
Classifier: Programming Language :: Python :: 3.12
Classifier: Programming Language :: Python :: 3.13
Classifier: Topic :: Software Development :: Libraries
Requires-Dist: cdo-local-uuid (>=0.5.0,<0.6.0)
Requires-Dist: pytz (>=2023.3.post1,<2024.0)
Project-URL: Repository, https://github.com/casework/CASE-Mapping-Python
